syne/__init__.py
syne/__main__.py
syne/playsound.py
syne/soundpoint.py
syne/synepoint.py
syne/utils.py
syne-0.0.1.dist-info/METADATA
syne-0.0.1.dist-info/RECORD
syne-0.0.1.dist-info/WHEEL
syne-0.0.1.dist-info/top_level.txt
