Metadata-Version: 2.1
Name: syne
Version: 0.0.1
Summary: synesthesia-based debugging
Home-page: https://github.com/aluriak/syne
Author: Lucas Bourneuf
Author-email: lucas.bourneuf@laposte.net
License: GPL
Keywords: debugging,synesthesia
Platform: UNKNOWN
Classifier: Development Status :: 3 - Alpha
Classifier: Intended Audience :: Developers
Classifier: Programming Language :: Python :: 3
Classifier: Programming Language :: Python :: 3.5
Classifier: License :: OSI Approved :: MIT License
Requires-Dist: magwitch (==0.1.0)
Requires-Dist: musthe (==1.0.0)
Requires-Dist: numpy (==1.14.5)
Requires-Dist: PyAudio (==0.2.11)
Requires-Dist: pytest (==3.6.3)
